ptarcade/__init__.py
ptarcade/chains_utils.py
ptarcade/data/__init__.py
ptarcade/data/default_config.py
ptarcade/data/g_star.dat
ptarcade/ent_mod.py
ptarcade/fast_interpolate.py
ptarcade/input_handler.py
ptarcade/models_utils.py
ptarcade/plot_utils.py
ptarcade/pta_importer.py
ptarcade/sampler.py
ptarcade/signal_builder.py
ptarcade-1.1.5.dist-info/WHEEL
ptarcade-1.1.5.dist-info/entry_points.txt
ptarcade-1.1.5.dist-info/METADATA
ptarcade-1.1.5.dist-info/RECORD
